fingerpaint/__init__.py
fingerpaint/fingerpaint.py
fingerpaint/data/fix_permissions.sh
fingerpaint-1.2.7.dist-info/LICENSE
fingerpaint-1.2.7.dist-info/METADATA
fingerpaint-1.2.7.dist-info/WHEEL
fingerpaint-1.2.7.dist-info/entry_points.txt
fingerpaint-1.2.7.dist-info/top_level.txt
fingerpaint-1.2.7.dist-info/RECORD
