Metadata-Version: 2.1
Name: fingerpaint
Version: 1.2.7
Summary: Draw using your laptop's touchpad
Home-page: https://github.com/Wazzaps/fingerpaint
Author: David Shlemayev
Author-email: david.shlemayev@gmail.com
License: UNKNOWN
Platform: UNKNOWN
Classifier: Programming Language :: Python :: 3
Classifier: License :: OSI Approved :: GNU General Public License v2 (GPLv2)
Classifier: Environment :: X11 Applications
Classifier: Operating System :: POSIX :: Linux
Classifier: Intended Audience :: End Users/Desktop
Classifier: Topic :: Artistic Software
Classifier: Topic :: Multimedia :: Graphics :: Editors :: Raster-Based
Classifier: Topic :: Utilities
Requires-Python: >=3.7
License-File: LICENSE
Requires-Dist: Pillow (>=5.3.0)
Requires-Dist: evdev (>=1.3.0)
Requires-Dist: pyudev
